adofai/__init__.py
adofai/models.py
adofai/utils/__init__.py
adofai/utils/profile.py
adofai/utils/signing.py
adofai/utils/uuid.py
adofai-0.1.0.dev6.dist-info/LICENSE
adofai-0.1.0.dev6.dist-info/METADATA
adofai-0.1.0.dev6.dist-info/WHEEL
adofai-0.1.0.dev6.dist-info/RECORD
