Metadata-Version: 2.1
Name: adofai
Version: 0.1.0.dev6
Summary: Shared data model for authlib-injector yggdrasil implementation and Minecraft API services
Home-page: https://github.com/Silverteal/adofai
License: MIT
Keywords: minecraft,mc,authlib,authlib-injector,implementaion,abc,yggdrasil
Author: Silverteal
Author-email: 67404722+Silverteal@users.noreply.github.com
Requires-Python: >=3.12,<4.0
Classifier: License :: OSI Approved :: MIT License
Classifier: Programming Language :: Python :: 3
Classifier: Programming Language :: Python :: 3.12
Requires-Dist: pycryptodome (>=3.21.0,<4.0.0)
Project-URL: Repository, https://github.com/Silverteal/adofai
